odoo/addons/ssi_analytic_account_mass_assign/README.rst
odoo/addons/ssi_analytic_account_mass_assign/__init__.py
odoo/addons/ssi_analytic_account_mass_assign/__manifest__.py
odoo/addons/ssi_analytic_account_mass_assign/security/ir.model.access.csv
odoo/addons/ssi_analytic_account_mass_assign/security/res_group_data.xml
odoo/addons/ssi_analytic_account_mass_assign/static/description/icon.png
odoo/addons/ssi_analytic_account_mass_assign/wizards/__init__.py
odoo/addons/ssi_analytic_account_mass_assign/wizards/account_analytic_mass_assign.py
odoo/addons/ssi_analytic_account_mass_assign/wizards/account_analytic_mass_assign_view.xml
odoo14_addon_ssi_analytic_account_mass_assign-14.0.1.0.2.dev1.dist-info/METADATA
odoo14_addon_ssi_analytic_account_mass_assign-14.0.1.0.2.dev1.dist-info/WHEEL
odoo14_addon_ssi_analytic_account_mass_assign-14.0.1.0.2.dev1.dist-info/top_level.txt
odoo14_addon_ssi_analytic_account_mass_assign-14.0.1.0.2.dev1.dist-info/RECORD
